pir_optics/__init__.py
pir_optics/pixel_array.py
pir_optics/pixel_irradiance.py
pir_optics/docs/PIR_theory_summary.md
pir_optics/docs/__init__.py
pir_optics-0.1.1.dist-info/METADATA
pir_optics-0.1.1.dist-info/WHEEL
pir_optics-0.1.1.dist-info/licenses/LICENSE
pir_optics-0.1.1.dist-info/RECORD
